horizonground/__init__.py
horizonground/clustering_modification.py
horizonground/conftest.py
horizonground/lumfunc_likelihood.py
horizonground/lumfunc_modeller.py
horizonground/utils.py
horizonground/tests/__init__.py
horizonground/tests/test_clustering_modification.py
horizonground/tests/test_lumfunc_likelihood.py
horizonground/tests/test_lumfunc_modeller.py
HorizonGRound-0.1.1.dist-info/LICENCE
HorizonGRound-0.1.1.dist-info/METADATA
HorizonGRound-0.1.1.dist-info/WHEEL
HorizonGRound-0.1.1.dist-info/top_level.txt
HorizonGRound-0.1.1.dist-info/RECORD
