Metadata-Version: 2.1
Name: HorizonGRound
Version: 0.1.1
Summary: Forward-modelling of relativistic effects from the tracer luminosity function.
Home-page: https://github.com/MikeSWang/HorizonGRound/
Author: Mike S Wang
Author-email: mike.wang@port.ac.uk
License: GPLv3
Project-URL: Documentation, https://mikeswang.github.io/HorizonGRound
Project-URL: Source, https://github.com/MikeSWang/HorizonGRound/
Platform: UNKNOWN
Classifier: Programming Language :: Python :: 3
Classifier: License :: OSI Approved :: GNU General Public License v3 (GPLv3)
Classifier: Operating System :: OS Independent
Requires-Python: >=3.6
Requires-Dist: numpy
Requires-Dist: scipy
Requires-Dist: astropy
Requires-Dist: nbodykit
